flask_request_validator/__init__.py
flask_request_validator/after_param.py
flask_request_validator/dt_utils.py
flask_request_validator/error_formatter.py
flask_request_validator/exceptions.py
flask_request_validator/files.py
flask_request_validator/nested_json.py
flask_request_validator/rules.py
flask_request_validator/valid_request.py
flask_request_validator/validator.py
flask_request_validator-4.4.0.dist-info/LICENSE
flask_request_validator-4.4.0.dist-info/METADATA
flask_request_validator-4.4.0.dist-info/WHEEL
flask_request_validator-4.4.0.dist-info/top_level.txt
flask_request_validator-4.4.0.dist-info/RECORD
