Metadata-Version: 2.1
Name: flask_request_validator
Version: 4.4.0
Summary: Flask request data validation
Home-page: https://github.com/d-ganchar/flask_request_validator
Author: Danila Ganchar
Author-email: danila.ganchar@gmail.com
License: MIT
Keywords: flask request validation
Classifier: Development Status :: 5 - Production/Stable
Classifier: Framework :: Flask
Classifier: Programming Language :: Python :: 3.7
Classifier: Programming Language :: Python :: 3.8
Classifier: Programming Language :: Python :: 3.9
Classifier: Programming Language :: Python :: 3.10
Classifier: Programming Language :: Python :: 3.11
License-File: LICENSE
Requires-Dist: flask
